LICENSE.txt
MANIFEST.in
README.rst
setup.cfg
setup.py
Transilien_Domoticz/__init__.py
Transilien_Domoticz/conf.cfg
Transilien_Domoticz/transilien.py
Transilien_Domoticz.egg-info/PKG-INFO
Transilien_Domoticz.egg-info/SOURCES.txt
Transilien_Domoticz.egg-info/dependency_links.txt
Transilien_Domoticz.egg-info/entry_points.txt
Transilien_Domoticz.egg-info/top_level.txt