Metadata-Version: 1.1
Name: Transilien-Domoticz
Version: 0.0.1
Summary: A Python script for use transilien.com API with Domoticz.
Home-page: https://github.com/matleses/Transilien-Domoticz
Author: Treussart Matthieu
Author-email: matthieu@treussart.com
License: MIT
Keywords: Domoticz Transilien SNCF
Platform: UNKNOWN
Classifier: Development Status :: 5 - Production/Stable
Classifier: Intended Audience :: Developers
Classifier: Topic :: Home Automation
Classifier: License :: OSI Approved :: MIT License
Classifier: Programming Language :: Python :: 3
